shedskin/__init__.py
shedskin/__main__.py
shedskin/ast_utils.py
shedskin/cmake.py
shedskin/config.py
shedskin/cpp.py
shedskin/error.py
shedskin/extmod.py
shedskin/graph.py
shedskin/infer.py
shedskin/lib/__init__.py
shedskin/lib/array.cpp
shedskin/lib/array.hpp
shedskin/lib/array.py
shedskin/lib/base64.cpp
shedskin/lib/base64.hpp
shedskin/lib/base64.py
shedskin/lib/binascii.cpp
shedskin/lib/binascii.hpp
shedskin/lib/binascii.py
shedskin/lib/bisect.cpp
shedskin/lib/bisect.hpp
shedskin/lib/bisect.py
shedskin/lib/builtin/bool.cpp
shedskin/lib/builtin/bool.hpp
shedskin/lib/builtin/bytes.cpp
shedskin/lib/builtin/bytes.hpp
shedskin/lib/builtin/compare.hpp
shedskin/lib/builtin/complex.cpp
shedskin/lib/builtin/complex.hpp
shedskin/lib/builtin/copy.hpp
shedskin/lib/builtin/dict.hpp
shedskin/lib/builtin/exception.cpp
shedskin/lib/builtin/exception.hpp
shedskin/lib/builtin/extmod.hpp
shedskin/lib/builtin/file.cpp
shedskin/lib/builtin/file.hpp
shedskin/lib/builtin/format.cpp
shedskin/lib/builtin/format.hpp
shedskin/lib/builtin/function.cpp
shedskin/lib/builtin/function.hpp
shedskin/lib/builtin/hash.hpp
shedskin/lib/builtin/iter.hpp
shedskin/lib/builtin/list.hpp
shedskin/lib/builtin/math.cpp
shedskin/lib/builtin/math.hpp
shedskin/lib/builtin/set.hpp
shedskin/lib/builtin/str.cpp
shedskin/lib/builtin/str.hpp
shedskin/lib/builtin/tuple.hpp
shedskin/lib/builtin.cpp
shedskin/lib/builtin.hpp
shedskin/lib/builtin.py
shedskin/lib/collections.cpp
shedskin/lib/collections.hpp
shedskin/lib/collections.py
shedskin/lib/colorsys.cpp
shedskin/lib/colorsys.hpp
shedskin/lib/colorsys.py
shedskin/lib/configparser.cpp
shedskin/lib/configparser.hpp
shedskin/lib/configparser.py
shedskin/lib/copy.cpp
shedskin/lib/copy.hpp
shedskin/lib/copy.py
shedskin/lib/csv.cpp
shedskin/lib/csv.hpp
shedskin/lib/csv.py
shedskin/lib/datetime.cpp
shedskin/lib/datetime.hpp
shedskin/lib/datetime.py
shedskin/lib/fnmatch.cpp
shedskin/lib/fnmatch.hpp
shedskin/lib/fnmatch.py
shedskin/lib/functools.cpp
shed_skin-0.9.11.dist-info/METADATA
shed_skin-0.9.11.dist-info/WHEEL
shed_skin-0.9.11.dist-info/entry_points.txt
shed_skin-0.9.11.dist-info/licenses/LICENSE
shed_skin-0.9.11.dist-info/RECORD
