Metadata-Version: 2.4
Name: shed-skin
Version: 0.9.11
Summary: Shed Skin is a restricted-Python-to-C++ compiler.
License: GNU GPL version 3
License-File: LICENSE
Author: Mark Dufour and contributors
Requires-Python: >=3.8,<4.0
Classifier: License :: Other/Proprietary License
Classifier: Programming Language :: Python :: 3
Classifier: Programming Language :: Python :: 3.8
Classifier: Programming Language :: Python :: 3.9
Classifier: Programming Language :: Python :: 3.10
Classifier: Programming Language :: Python :: 3.11
Classifier: Programming Language :: Python :: 3.12
Classifier: Programming Language :: Python :: 3.13
Classifier: Programming Language :: Python :: 3.14
Classifier: Topic :: Software Development :: Compilers
Classifier: Topic :: Software Development :: Libraries :: Python Modules
Project-URL: Bug Tracker, https://github.com/shedskin/shedskin/issues
Project-URL: Documentation, https://shedskin.readthedocs.io
Project-URL: Homepage, https://shedskin.github.io
Project-URL: Repository, https://github.com/shedskin/shedskin
